src/__init__.py
src/croping.py
whitecrop3d-0.3.1.dist-info/METADATA
whitecrop3d-0.3.1.dist-info/WHEEL
whitecrop3d-0.3.1.dist-info/entry_points.txt
whitecrop3d-0.3.1.dist-info/top_level.txt
whitecrop3d-0.3.1.dist-info/RECORD
