Metadata-Version: 2.1
Name: whitecrop3d
Version: 0.3.1
Summary: Crops unnecessary white background from images. Meant to be for 3D models previews.
Home-page: https://github.com/cisar2218/whitecrop3d
Author: Dušan Jánsky
Author-email: cisar2218@gmail.com
